justnimbus/__init__.py
justnimbus/exceptions.py
justnimbus/model.py
justnimbus-0.7.3.dist-info/LICENSE.md
justnimbus-0.7.3.dist-info/METADATA
justnimbus-0.7.3.dist-info/WHEEL
justnimbus-0.7.3.dist-info/RECORD
