Metadata-Version: 2.1
Name: justnimbus
Version: 0.7.3
Summary: A Python Wrapper for the Just Nimbus API
Home-page: https://github.com/kvanzuijlen/justnimbus
Author: kvanzuijlen
Author-email: 8818390+kvanzuijlen@users.noreply.github.com
Requires-Python: >=3.10,<4.0
Classifier: Programming Language :: Python :: 3
Classifier: Programming Language :: Python :: 3.10
Classifier: Programming Language :: Python :: 3.11
Classifier: Programming Language :: Python :: 3.12
Requires-Dist: requests (>=2.27.1,<3.0.0)
Project-URL: Repository, https://github.com/kvanzuijlen/justnimbus
